Workbook

Sheet Parameters
A1: Parameter | B1: Value | C1: Description
A2: Amazon_Commission_pct | B2: 0.18 | C2: Amazon marketplace commission rate (decimal)
A3: ONDC_Commission_pct | B3: 0.06 | C3: ONDC network commission rate (decimal)
A4: Payment_Fee_pct | B4: 0.02 | C4: Payment gateway fee rate (decimal)
A5: Packaging_per_unit | B5: 12 | C5: Packaging cost per unit (INR)
A6: Other_Fees_per_unit | B6: 5 | C6: Other fees per unit (INR)
A7: CAC_Amazon_per_unit | B7: 90 | C7: Customer Acquisition Cost per unit - Amazon (INR)
A8: CAC_ONDC_per_unit | B8: 100 | C8: Customer Acquisition Cost per unit - ONDC (INR)
A9: Default_Fixed_Costs_monthly | B9: 50000 | C9: Monthly fixed costs (INR)

Sheet Product_Data
A1: Product_Name | B1: Size | C1: Selling_Price | D1: Estimated_Weight_g | E1: Monthly_Sales_Units | F1: Cost_of_Goods_est | G1: Logistics_Cost
A2: Mamaearth Onion Hair Oil for Hair Growth & Hair Fall Control | B2: 100ml | C2: 399 | D2: 100 | E2: 15000 | F2: 119.7 | G2: 15
A3: Mamaearth Vitamin C Face Wash with Vitamin C & Turmeric | B3: 100ml | C3: 199 | D3: 100 | E3: 25000 | F3: 59.7 | G3: 15
A4: Mamaearth Ubtan Face Wash with Turmeric & Saffron | B4: 100ml | C4: 199 | D4: 100 | E4: 22000 | F4: 59.7 | G4: 15
A5: Mamaearth Rice Face Scrub for Tan Removal | B5: 100g | C5: 299 | D5: 100 | E5: 12000 | F5: 89.7 | G5: 15
A6: Mamaearth Vitamin C Face Cream with Vitamin C & SPF 30 | B6: 50g | C6: 449 | D6: 50 | E6: 18000 | F6: 134.7 | G6: 15
A7: Mamaearth Onion Shampoo for Hair Growth & Hair Fall Control | B7: 250ml | C7: 349 | D7: 250 | E7: 20000 | F7: 104.7 | G7: 15
A8: Mamaearth Ubtan Face Cream with Turmeric & Saffron | B8: 50g | C8: 449 | D8: 50 | E8: 16000 | F8: 134.7 | G8: 15
A9: Mamaearth Tea Tree Face Wash for Acne & Pimples | B9: 100ml | C9: 199 | D9: 100 | E9: 19000 | F9: 59.7 | G9: 15
A10: Mamaearth Aloe Vera Face Wash for Hydration | B10: 100ml | C10: 199 | D10: 100 | E10: 17000 | F10: 59.7 | G10: 15
A11: Mamaearth Vitamin C Face Serum with Vitamin C & Turmeric | B11: 30ml | C11: 599 | D11: 30 | E11: 14000 | F11: 179.7 | G11: 15

Sheet Unit_Economics
A1: Product_Name | B1: Selling_Price | C1: Cost_of_Goods | D1: Amazon_Commission_amt | E1: ONDC_Commission_amt | F1: Payment_Gateway_Fee | G1: Logistics_Cost | H1: Packaging_Cost | I1: Other_Fees | J1: CAC_Amazon | K1: CAC_ONDC | L1: Total_Cost_Amazon | M1: Total_Cost_ONDC | N1: Profit_per_unit_Amazon | O1: Profit_per_unit_ONDC | P1: Profit_Change_pct | Q1: Monthly_Profit_Amazon | R1: Monthly_Profit_ONDC
A2: Mamaearth Onion Hair Oil for Hair Growth & Hair Fall Control | B2: =Product_Data!C2 | C2: =Product_Data!F2 | D2: =B2*Parameters!B2 | E2: =B2*Parameters!B3 | F2: =B2*Parameters!B4 | G2: =Product_Data!G2 | H2: =Parameters!B5 | I2: =Parameters!B6 | J2: =Parameters!B7 | K2: =Parameters!B8 | L2: =C2+D2+F2+G2+H2+I2+J2 | M2: =C2+E2+F2+G2+H2+I2+K2 | N2: =B2-L2 | O2: =B2-M2 | P2: =(O2-N2)/ABS(N2)*100 | Q2: =N2*Product_Data!E2 | R2: =O2*Product_Data!E2
A3: Mamaearth Vitamin C Face Wash with Vitamin C & Turmeric | B3: =Product_Data!C3 | C3: =Product_Data!F3 | D3: =B3*Parameters!B2 | E3: =B3*Parameters!B3 | F3: =B3*Parameters!B4 | G3: =Product_Data!G3 | H3: =Parameters!B5 | I3: =Parameters!B6 | J3: =Parameters!B7 | K3: =Parameters!B8 | L3: =C3+D3+F3+G3+H3+I3+J3 | M3: =C3+E3+F3+G3+H3+I3+K3 | N3: =B3-L3 | O3: =B3-M3 | P3: =(O3-N3)/ABS(N3)*100 | Q3: =N3*Product_Data!E3 | R3: =O3*Product_Data!E3
A4: Mamaearth Ubtan Face Wash with Turmeric & Saffron | B4: =Product_Data!C4 | C4: =Product_Data!F4 | D4: =B4*Parameters!B2 | E4: =B4*Parameters!B3 | F4: =B4*Parameters!B4 | G4: =Product_Data!G4 | H4: =Parameters!B5 | I4: =Parameters!B6 | J4: =Parameters!B7 | K4: =Parameters!B8 | L4: =C4+D4+F4+G4+H4+I4+J4 | M4: =C4+E4+F4+G4+H4+I4+K4 | N4: =B4-L4 | O4: =B4-M4 | P4: =(O4-N4)/ABS(N4)*100 | Q4: =N4*Product_Data!E4 | R4: =O4*Product_Data!E4
A5: Mamaearth Rice Face Scrub for Tan Removal | B5: =Product_Data!C5 | C5: =Product_Data!F5 | D5: =B5*Parameters!B2 | E5: =B5*Parameters!B3 | F5: =B5*Parameters!B4 | G5: =Product_Data!G5 | H5: =Parameters!B5 | I5: =Parameters!B6 | J5: =Parameters!B7 | K5: =Parameters!B8 | L5: =C5+D5+F5+G5+H5+I5+J5 | M5: =C5+E5+F5+G5+H5+I5+K5 | N5: =B5-L5 | O5: =B5-M5 | P5: =(O5-N5)/ABS(N5)*100 | Q5: =N5*Product_Data!E5 | R5: =O5*Product_Data!E5
A6: Mamaearth Vitamin C Face Cream with Vitamin C & SPF 30 | B6: =Product_Data!C6 | C6: =Product_Data!F6 | D6: =B6*Parameters!B2 | E6: =B6*Parameters!B3 | F6: =B6*Parameters!B4 | G6: =Product_Data!G6 | H6: =Parameters!B5 | I6: =Parameters!B6 | J6: =Parameters!B7 | K6: =Parameters!B8 | L6: =C6+D6+F6+G6+H6+I6+J6 | M6: =C6+E6+F6+G6+H6+I6+K6 | N6: =B6-L6 | O6: =B6-M6 | P6: =(O6-N6)/ABS(N6)*100 | Q6: =N6*Product_Data!E6 | R6: =O6*Product_Data!E6
A7: Mamaearth Onion Shampoo for Hair Growth & Hair Fall Control | B7: =Product_Data!C7 | C7: =Product_Data!F7 | D7: =B7*Parameters!B2 | E7: =B7*Parameters!B3 | F7: =B7*Parameters!B4 | G7: =Product_Data!G7 | H7: =Parameters!B5 | I7: =Parameters!B6 | J7: =Parameters!B7 | K7: =Parameters!B8 | L7: =C7+D7+F7+G7+H7+I7+J7 | M7: =C7+E7+F7+G7+H7+I7+K7 | N7: =B7-L7 | O7: =B7-M7 | P7: =(O7-N7)/ABS(N7)*100 | Q7: =N7*Product_Data!E7 | R7: =O7*Product_Data!E7
A8: Mamaearth Ubtan Face Cream with Turmeric & Saffron | B8: =Product_Data!C8 | C8: =Product_Data!F8 | D8: =B8*Parameters!B2 | E8: =B8*Parameters!B3 | F8: =B8*Parameters!B4 | G8: =Product_Data!G8 | H8: =Parameters!B5 | I8: =Parameters!B6 | J8: =Parameters!B7 | K8: =Parameters!B8 | L8: =C8+D8+F8+G8+H8+I8+J8 | M8: =C8+E8+F8+G8+H8+I8+K8 | N8: =B8-L8 | O8: =B8-M8 | P8: =(O8-N8)/ABS(N8)*100 | Q8: =N8*Product_Data!E8 | R8: =O8*Product_Data!E8
A9: Mamaearth Tea Tree Face Wash for Acne & Pimples | B9: =Product_Data!C9 | C9: =Product_Data!F9 | D9: =B9*Parameters!B2 | E9: =B9*Parameters!B3 | F9: =B9*Parameters!B4 | G9: =Product_Data!G9 | H9: =Parameters!B5 | I9: =Parameters!B6 | J9: =Parameters!B7 | K9: =Parameters!B8 | L9: =C9+D9+F9+G9+H9+I9+J9 | M9: =C9+E9+F9+G9+H9+I9+K9 | N9: =B9-L9 | O9: =B9-M9 | P9: =(O9-N9)/ABS(N9)*100 | Q9: =N9*Product_Data!E9 | R9: =O9*Product_Data!E9
A10: Mamaearth Aloe Vera Face Wash for Hydration | B10: =Product_Data!C10 | C10: =Product_Data!F10 | D10: =B10*Parameters!B2 | E10: =B10*Parameters!B3 | F10: =B10*Parameters!B4 | G10: =Product_Data!G10 | H10: =Parameters!B5 | I10: =Parameters!B6 | J10: =Parameters!B7 | K10: =Parameters!B8 | L10: =C10+D10+F10+G10+H10+I10+J10 | M10: =C10+E10+F10+G10+H10+I10+K10 | N10: =B10-L10 | O10: =B10-M10 | P10: =(O10-N10)/ABS(N10)*100 | Q10: =N10*Product_Data!E10 | R10: =O10*Product_Data!E10
A11: Mamaearth Vitamin C Face Serum with Vitamin C & Turmeric | B11: =Product_Data!C11 | C11: =Product_Data!F11 | D11: =B11*Parameters!B2 | E11: =B11*Parameters!B3 | F11: =B11*Parameters!B4 | G11: =Product_Data!G11 | H11: =Parameters!B5 | I11: =Parameters!B6 | J11: =Parameters!B7 | K11: =Parameters!B8 | L11: =C11+D11+F11+G11+H11+I11+J11 | M11: =C11+E11+F11+G11+H11+I11+K11 | N11: =B11-L11 | O11: =B11-M11 | P11: =(O11-N11)/ABS(N11)*100 | Q11: =N11*Product_Data!E11 | R11: =O11*Product_Data!E11

Sheet Scenario_Analysis
A1: Scenario Parameter Changes (%):
A2: CAC Amazon % Change | B2: 0
A3: CAC ONDC % Change | B3: 0
A4: Logistics % Change | B4: 0
A5: Product_Name | B5: Base_Profit_ONDC | C5: Adjusted_CAC_ONDC | D5: Adjusted_Logistics | E5: Adjusted_ONDC_Comm | F5: Adjusted_Total_Cost_ONDC | G5: Adjusted_Profit_ONDC | H5: Profit_Change_vs_Base
A6: Mamaearth Onion Hair Oil for Hair Growth & Hair Fall Control | B6: =Unit_Economics!O6 | C6: =Parameters!B8*(1+B4) | D6: =Unit_Economics!G6*(1+B5) | E6: =Unit_Economics!B6*Parameters!B3*(1+B6) | F6: =Unit_Economics!C6+E6+Unit_Economics!F6+D6+C6+Parameters!B5+Parameters!B6 | G6: =Unit_Economics!B6-F6 | H6: =(G6-B6)/ABS(B6)*100
A7: Mamaearth Vitamin C Face Wash with Vitamin C & Turmeric | B7: =Unit_Economics!O7 | C7: =Parameters!B8*(1+B4) | D7: =Unit_Economics!G7*(1+B5) | E7: =Unit_Economics!B7*Parameters!B3*(1+B6) | F7: =Unit_Economics!C7+E7+Unit_Economics!F7+D7+C7+Parameters!B5+Parameters!B6 | G7: =Unit_Economics!B7-F7 | H7: =(G7-B7)/ABS(B7)*100
A8: Mamaearth Ubtan Face Wash with Turmeric & Saffron | B8: =Unit_Economics!O8 | C8: =Parameters!B8*(1+B4) | D8: =Unit_Economics!G8*(1+B5) | E8: =Unit_Economics!B8*Parameters!B3*(1+B6) | F8: =Unit_Economics!C8+E8+Unit_Economics!F8+D8+C8+Parameters!B5+Parameters!B6 | G8: =Unit_Economics!B8-F8 | H8: =(G8-B8)/ABS(B8)*100
A9: Mamaearth Rice Face Scrub for Tan Removal | B9: =Unit_Economics!O9 | C9: =Parameters!B8*(1+B4) | D9: =Unit_Economics!G9*(1+B5) | E9: =Unit_Economics!B9*Parameters!B3*(1+B6) | F9: =Unit_Economics!C9+E9+Unit_Economics!F9+D9+C9+Parameters!B5+Parameters!B6 | G9: =Unit_Economics!B9-F9 | H9: =(G9-B9)/ABS(B9)*100
A10: Mamaearth Vitamin C Face Cream with Vitamin C & SPF 30 | B10: =Unit_Economics!O10 | C10: =Parameters!B8*(1+B4) | D10: =Unit_Economics!G10*(1+B5) | E10: =Unit_Economics!B10*Parameters!B3*(1+B6) | F10: =Unit_Economics!C10+E10+Unit_Economics!F10+D10+C10+Parameters!B5+Parameters!B6 | G10: =Unit_Economics!B10-F10 | H10: =(G10-B10)/ABS(B10)*100
A11: Mamaearth Onion Shampoo for Hair Growth & Hair Fall Control | B11: =Unit_Economics!O11 | C11: =Parameters!B8*(1+B4) | D11: =Unit_Economics!G11*(1+B5) | E11: =Unit_Economics!B11*Parameters!B3*(1+B6) | F11: =Unit_Economics!C11+E11+Unit_Economics!F11+D11+C11+Parameters!B5+Parameters!B6 | G11: =Unit_Economics!B11-F11 | H11: =(G11-B11)/ABS(B11)*100
A12: Mamaearth Ubtan Face Cream with Turmeric & Saffron | B12: =Unit_Economics!O12 | C12: =Parameters!B8*(1+B4) | D12: =Unit_Economics!G12*(1+B5) | E12: =Unit_Economics!B12*Parameters!B3*(1+B6) | F12: =Unit_Economics!C12+E12+Unit_Economics!F12+D12+C12+Parameters!B5+Parameters!B6 | G12: =Unit_Economics!B12-F12 | H12: =(G12-B12)/ABS(B12)*100
A13: Mamaearth Tea Tree Face Wash for Acne & Pimples | B13: =Unit_Economics!O13 | C13: =Parameters!B8*(1+B4) | D13: =Unit_Economics!G13*(1+B5) | E13: =Unit_Economics!B13*Parameters!B3*(1+B6) | F13: =Unit_Economics!C13+E13+Unit_Economics!F13+D13+C13+Parameters!B5+Parameters!B6 | G13: =Unit_Economics!B13-F13 | H13: =(G13-B13)/ABS(B13)*100
A14: Mamaearth Aloe Vera Face Wash for Hydration | B14: =Unit_Economics!O14 | C14: =Parameters!B8*(1+B4) | D14: =Unit_Economics!G14*(1+B5) | E14: =Unit_Economics!B14*Parameters!B3*(1+B6) | F14: =Unit_Economics!C14+E14+Unit_Economics!F14+D14+C14+Parameters!B5+Parameters!B6 | G14: =Unit_Economics!B14-F14 | H14: =(G14-B14)/ABS(B14)*100
A15: Mamaearth Vitamin C Face Serum with Vitamin C & Turmeric | B15: =Unit_Economics!O15 | C15: =Parameters!B8*(1+B4) | D15: =Unit_Economics!G15*(1+B5) | E15: =Unit_Economics!B15*Parameters!B3*(1+B6) | F15: =Unit_Economics!C15+E15+Unit_Economics!F15+D15+C15+Parameters!B5+Parameters!B6 | G15: =Unit_Economics!B15-F15 | H15: =(G15-B15)/ABS(B15)*100

Sheet Break_Even
A1: Fixed Costs (Monthly): | B1: =Parameters!B9
A3: Product_Name | B3: Selling_Price | C3: Total_Variable_Cost_ONDC | D3: Contribution_per_unit_ONDC | E3: Break_even_units | F3: Break_even_revenue
A4: Mamaearth Onion Hair Oil for Hair Growth & Hair Fall Control | B4: =Unit_Economics!B4 | C4: =Unit_Economics!M4 | D4: =B4-C4 | E4: =IF(D4>0, B1/D4, 0) | F4: =E4*B4
A5: Mamaearth Vitamin C Face Wash with Vitamin C & Turmeric | B5: =Unit_Economics!B5 | C5: =Unit_Economics!M5 | D5: =B5-C5 | E5: =IF(D5>0, B1/D5, 0) | F5: =E5*B5
A6: Mamaearth Ubtan Face Wash with Turmeric & Saffron | B6: =Unit_Economics!B6 | C6: =Unit_Economics!M6 | D6: =B6-C6 | E6: =IF(D6>0, B1/D6, 0) | F6: =E6*B6
A7: Mamaearth Rice Face Scrub for Tan Removal | B7: =Unit_Economics!B7 | C7: =Unit_Economics!M7 | D7: =B7-C7 | E7: =IF(D7>0, B1/D7, 0) | F7: =E7*B7
A8: Mamaearth Vitamin C Face Cream with Vitamin C & SPF 30 | B8: =Unit_Economics!B8 | C8: =Unit_Economics!M8 | D8: =B8-C8 | E8: =IF(D8>0, B1/D8, 0) | F8: =E8*B8
A9: Mamaearth Onion Shampoo for Hair Growth & Hair Fall Control | B9: =Unit_Economics!B9 | C9: =Unit_Economics!M9 | D9: =B9-C9 | E9: =IF(D9>0, B1/D9, 0) | F9: =E9*B9
A10: Mamaearth Ubtan Face Cream with Turmeric & Saffron | B10: =Unit_Economics!B10 | C10: =Unit_Economics!M10 | D10: =B10-C10 | E10: =IF(D10>0, B1/D10, 0) | F10: =E10*B10
A11: Mamaearth Tea Tree Face Wash for Acne & Pimples | B11: =Unit_Economics!B11 | C11: =Unit_Economics!M11 | D11: =B11-C11 | E11: =IF(D11>0, B1/D11, 0) | F11: =E11*B11
A12: Mamaearth Aloe Vera Face Wash for Hydration | B12: =Unit_Economics!B12 | C12: =Unit_Economics!M12 | D12: =B12-C12 | E12: =IF(D12>0, B1/D12, 0) | F12: =E12*B12
A13: Mamaearth Vitamin C Face Serum with Vitamin C & Turmeric | B13: =Unit_Economics!B13 | C13: =Unit_Economics!M13 | D13: =B13-C13 | E13: =IF(D13>0, B1/D13, 0) | F13: =E13*B13

Sheet Dashboard
A1: ONDC vs Amazon Unit Economics Dashboard
A3: Key Metrics
A4: Average Profit per Unit (Amazon) | B4: =AVERAGE(Unit_Economics!N2:N11)
A5: Average Profit per Unit (ONDC) | B5: =AVERAGE(Unit_Economics!O2:O11)
A6: Average Profit Increase % | B6: =AVERAGE(Unit_Economics!P2:P11)
A7: Total Monthly Profit (Amazon) | B7: =SUM(Unit_Economics!Q2:Q11)
A8: Total Monthly Profit (ONDC) | B8: =SUM(Unit_Economics!R2:R11)
A9: Total Monthly Profit Increase | B9: =E7-E6
A10: Best Performing Product (ONDC) | B10: =INDEX(Unit_Economics!A2:A11,MATCH(MAX(Unit_Economics!O2:O11),Unit_Economics!O2:O11,0))
A13: Charts
